ansipix/__init__.py
ansipix/animation_player.py
ansipix/cli.py
ansipix/debug_logger.py
ansipix/dimensions.py
ansipix/image_player.py
ansipix/image_process.py
ansipix/media_loader.py
ansipix/offline_renderer.py
ansipix/render.py
ansipix/term_utils.py
ansipix-1.0.1.dist-info/licenses/LICENSE
ansipix-1.0.1.dist-info/METADATA
ansipix-1.0.1.dist-info/WHEEL
ansipix-1.0.1.dist-info/entry_points.txt
ansipix-1.0.1.dist-info/top_level.txt
ansipix-1.0.1.dist-info/RECORD
