Metadata-Version: 2.4
Name: ansipix
Version: 1.0.1
Summary: A high-performance terminal media viewer for playing images, GIFs, and videos in 24-bit truecolor.
Author-email: EdgeOfAssembly <haxbox2000@gmail.com>
License: ansipix
Project-URL: Homepage, https://github.com/EdgeOfAssembly/ansipix
Project-URL: Bug Tracker, https://github.com/EdgeOfAssembly/ansipix/issues
Keywords: terminal,tui,video,gif,image,ansi,truecolor,viewer
Classifier: Development Status :: 4 - Beta
Classifier: Environment :: Console
Classifier: Intended Audience :: Developers
Classifier: Intended Audience :: End Users/Desktop
Classifier: License :: OSI Approved :: GNU General Public License v3 (GPLv3)
Classifier: Operating System :: OS Independent
Classifier: Programming Language :: Python :: 3
Classifier: Programming Language :: Python :: 3.8
Classifier: Programming Language :: Python :: 3.9
Classifier: Programming Language :: Python :: 3.10
Classifier: Programming Language :: Python :: 3.11
Classifier: Topic :: Multimedia :: Graphics :: Viewers
Classifier: Topic :: Multimedia :: Video :: Display
Classifier: Topic :: Terminals
Requires-Python: >=3.8
License-File: LICENSE
Requires-Dist: opencv-python
Requires-Dist: numpy
Requires-Dist: Pillow
Dynamic: license-file
